piminder_helpers/__init__.py
piminder_helpers/classes.py
piminder_monitor/__main__.py
piminder_monitor/font.py
piminder_monitor/screendriver.py
piminder_service/__init__.py
piminder_service/app.py
piminder_service/run.py
piminder-1.0.6.dist-info/METADATA
piminder-1.0.6.dist-info/WHEEL
piminder-1.0.6.dist-info/top_level.txt
piminder-1.0.6.dist-info/RECORD
