Metadata-Version: 2.1
Name: piminder
Version: 1.0.6
Summary: Piminder is a special network messanging service for status alerts.
Home-page: https://www.github.com/zadammac/Piminder
Author: Zac Adam-MacEwen
Author-email: zadammac@kenshosec.com
License: UNKNOWN
Platform: UNKNOWN
Requires-Dist: bcrypt
Requires-Dist: flask
Requires-Dist: flask-restful
Requires-Dist: pymysql
